white_rock_connection/__init__.py
white_rock_connection/messages/__init__.py
white_rock_connection/messages/telegram.py
white_rock_connection/redisconn/__init__.py
white_rock_connection/redisconn/stream_consumer.py
white_rock_connection/redisconn/stream_producer.py
white_rock_connection-0.1.dist-info/METADATA
white_rock_connection-0.1.dist-info/WHEEL
white_rock_connection-0.1.dist-info/top_level.txt
white_rock_connection-0.1.dist-info/RECORD
